LICENSE
MANIFEST.in
README.md
package.json
setup.py
dash_react_wordcloud/DashReactWordcloud.py
dash_react_wordcloud/Wordcloud.py
dash_react_wordcloud/__init__.py
dash_react_wordcloud/_imports_.py
dash_react_wordcloud/dash_react_wordcloud.min.js
dash_react_wordcloud/dash_react_wordcloud.min.js.map
dash_react_wordcloud/metadata.json
dash_react_wordcloud/package-info.json
dash_react_wordcloud.egg-info/PKG-INFO
dash_react_wordcloud.egg-info/SOURCES.txt
dash_react_wordcloud.egg-info/dependency_links.txt
dash_react_wordcloud.egg-info/top_level.txt