Metadata-Version: 1.1
Name: dash-react-wordcloud
Version: 0.0.1
Summary: A Dash wrapper for react-wordcloud by chrisrzhou (https://github.com/chrisrzhou/react-wordcloud), which itself is a React wrapper for D3 Wordcloud (https://www.d3-graph-gallery.com/wordcloud).
Home-page: UNKNOWN
Author: Zack Adlington <zack@zackcodes.com>
Author-email: UNKNOWN
License: MIT
Platform: UNKNOWN
Classifier: Framework :: Dash
